Metadata-Version: 1.0
Name: fkfyz-probability
Version: 0.1
Summary: Gaussian distributions
Home-page: UNKNOWN
Author: feng kai
Author-email: kaifeng0502@gmail.com
License: UNKNOWN
Platform: UNKNOWN
